{
	"name": "TRG_KHCDE_SAP_CAT_LOGISTICS_AUDIT_DAILY",
	"properties": {
		"description": "Daily Data Load of Control Tower Data for Audit_Logistics",
		"annotations": [],
		"runtimeState": "Started",
		"pipelines": [
			{
				"pipelineReference": {
					"referenceName": "PL_KHCDE_SAP_CATALYST_MASTER_POOL_LOAD",
					"type": "PipelineReference"
				},
				"parameters": {
					"ApplicationName": "audit_logistics",
					"DatasetGroup": "audit_otc",
					"SchemaName": "_SYS_BIC"
				}
			}
		],
		"type": "ScheduleTrigger",
		"typeProperties": {
			"recurrence": {
				"frequency": "Day",
				"interval": 1,
				"startTime": "2021-03-25T08:02:00",
				"timeZone": "Central Standard Time",
				"schedule": {
					"minutes": [
						30
					],
					"hours": [
						11
					]
				}
			}
		}
	}
}