{
	"name": "TRG_KHCDE_SAP_ARIBA_ANALYTICAL_API_TRANSACTION_DAILY",
	"properties": {
		"description": "The trigger runs the pipeline PL_KHCDE_SAP_ARIBA_ANALYTICAL_API_MASTER_POOL_LOAD at 5:00AM UTC to extract SAP Ariba Templates data from Ariba Analytical API.",
		"annotations": [],
		"runtimeState": "Started",
		"pipelines": [
			{
				"pipelineReference": {
					"referenceName": "PL_KHCDE_SAP_ARIBA_ANALYTICAL_API_MASTER_POOL_LOAD",
					"type": "PipelineReference"
				},
				"parameters": {
					"ApplicationName": "indirect_procurement",
					"DatasetGroup": "analytical_api",
					"to_emails": "s-khcde@kraftheinz.com",
					"email_notify_ind": "n",
					"SchemaName": "ARIBA"
				}
			}
		],
		"type": "ScheduleTrigger",
		"typeProperties": {
			"recurrence": {
				"frequency": "Day",
				"interval": 1,
				"startTime": "2021-09-27T14:27:00Z",
				"timeZone": "UTC",
				"schedule": {
					"minutes": [
						0
					],
					"hours": [
						5
					]
				}
			}
		}
	}
}