{
	"name": "PL_KHCDE_CA_PRODUCT_CUSTOMER_MASTER_POOL_LOAD",
	"properties": {
		"description": "This has 2 Pipelines to Process the data. 1. Ingest Data from RAW blob files to Snowflake Stage Tables and \n2. Transform the data from Stage Tables and load to the final base tables.",
		"activities": [
			{
				"name": "LU-Metadata",
				"description": "This activity pulls the entries from \norchestration metadata table",
				"type": "Lookup",
				"dependsOn": [
					{
						"activity": "SP-PipelineStart_Snowflake",
						"dependencyConditions": [
							"Succeeded"
						]
					}
				],
				"policy": {
					"timeout": "7.00:00:00",
					"retry": 5,
					"retryIntervalInSeconds": 30,
					"secureOutput": false,
					"secureInput": false
				},
				"userProperties": [],
				"typeProperties": {
					"source": {
						"type": "SqlServerSource",
						"sqlReaderQuery": {
							"value": "select * from khc_orchestration_metadata where application_name = '@{pipeline().parameters.ApplicationName}' and adf_trigger_name = '@{replace(pipeline().parameters.adf_trigger_name,'_trigger.txt','')}' and active_ind = 'y'",
							"type": "Expression"
						},
						"queryTimeout": "02:00:00",
						"partitionOption": "None"
					},
					"dataset": {
						"referenceName": "DS_KHCDE_GENERIC_MSSQL_Metadata",
						"type": "DatasetReference"
					},
					"firstRowOnly": false
				}
			},
			{
				"name": "EP-SnowflakeIngestion",
				"description": "This will perform DBT processing.",
				"type": "ExecutePipeline",
				"dependsOn": [
					{
						"activity": "LU-Metadata",
						"dependencyConditions": [
							"Succeeded"
						]
					}
				],
				"userProperties": [],
				"typeProperties": {
					"pipeline": {
						"referenceName": "PL_KHCDE_GENERIC_SnowflakeIngestion",
						"type": "PipelineReference"
					},
					"waitOnCompletion": true,
					"parameters": {
						"ApplicationName": {
							"value": "@{activity('LU-Metadata').output.value[0].application_name}",
							"type": "Expression"
						},
						"DatasetGroup": {
							"value": "@{activity('LU-Metadata').output.value[0].dataset_group}",
							"type": "Expression"
						},
						"ParameterJson": {
							"value": "@{activity('LU-Metadata').output.value[0].parameter_json}",
							"type": "Expression"
						}
					}
				}
			},
			{
				"name": "EP-DBT_Processing",
				"description": "This will perform DBT processing.",
				"type": "ExecutePipeline",
				"dependsOn": [
					{
						"activity": "EP-SnowflakeIngestion",
						"dependencyConditions": [
							"Succeeded"
						]
					}
				],
				"userProperties": [],
				"typeProperties": {
					"pipeline": {
						"referenceName": "PL_KHCDE_GENERIC_DBTProcessing",
						"type": "PipelineReference"
					},
					"waitOnCompletion": true,
					"parameters": {
						"ApplicationName": {
							"value": "@{activity('LU-Metadata').output.value[0].application_name}",
							"type": "Expression"
						},
						"DatasetGroup": {
							"value": "@{activity('LU-Metadata').output.value[0].dataset_group}",
							"type": "Expression"
						},
						"ParameterJson": {
							"value": "@{activity('LU-Metadata').output.value[0].parameter_json}",
							"type": "Expression"
						}
					}
				}
			},
			{
				"name": "SP-PipelineStart_Snowflake",
				"description": "This Activity logs starting of pipeline in khc_audit_log table.",
				"type": "SqlServerStoredProcedure",
				"dependsOn": [],
				"policy": {
					"timeout": "7.00:00:00",
					"retry": 5,
					"retryIntervalInSeconds": 30,
					"secureOutput": false,
					"secureInput": false
				},
				"userProperties": [],
				"typeProperties": {
					"storedProcedureName": "[dbo].[generic_pipeline_audit_log]",
					"storedProcedureParameters": {
						"action_ind": {
							"value": {
								"value": "I",
								"type": "Expression"
							},
							"type": "String"
						},
						"application_name": {
							"value": {
								"value": "@pipeline().parameters.ApplicationName",
								"type": "Expression"
							},
							"type": "String"
						},
						"pipeline_name": {
							"value": {
								"value": "@{pipeline().Pipeline}",
								"type": "Expression"
							},
							"type": "String"
						},
						"pipeline_run_id": {
							"value": {
								"value": "@{pipeline().RunId}",
								"type": "Expression"
							},
							"type": "String"
						},
						"pipeline_status": {
							"value": {
								"value": "Processing",
								"type": "Expression"
							},
							"type": "String"
						},
						"Dataset_name": {
							"value": {
								"value": "product_customer_master",
								"type": "Expression"
							},
							"type": "String"
						}
					}
				},
				"linkedServiceName": {
					"referenceName": "LS_SQL",
					"type": "LinkedServiceReference"
				}
			},
			{
				"name": "SP-ActivityFailed05",
				"description": "Snowflake ingestion activity failed",
				"type": "SqlServerStoredProcedure",
				"dependsOn": [
					{
						"activity": "EP-SnowflakeIngestion",
						"dependencyConditions": [
							"Failed"
						]
					}
				],
				"policy": {
					"timeout": "7.00:00:00",
					"retry": 5,
					"retryIntervalInSeconds": 30,
					"secureOutput": false,
					"secureInput": false
				},
				"userProperties": [],
				"typeProperties": {
					"storedProcedureName": "[dbo].[generic_activity_error_audit_log]",
					"storedProcedureParameters": {
						"activity_name": {
							"value": "EP_SnowflakeIngestion",
							"type": "String"
						},
						"activity_status": {
							"value": {
								"value": "Failed",
								"type": "Expression"
							},
							"type": "String"
						},
						"application_name": {
							"value": {
								"value": "@activity('LU-Metadata').output.value[0].application_name",
								"type": "Expression"
							},
							"type": "String"
						},
						"dataset_name": {
							"value": {
								"value": "@activity('LU-Metadata').output.value[0].dataset_group",
								"type": "Expression"
							},
							"type": "String"
						},
						"error_code": {
							"value": {
								"value": "N.A.",
								"type": "Expression"
							},
							"type": "String"
						},
						"error_detail": {
							"value": {
								"value": "N.A.",
								"type": "Expression"
							},
							"type": "String"
						},
						"pipeline_run_id": {
							"value": {
								"value": "@{pipeline().RunId}",
								"type": "Expression"
							},
							"type": "String"
						}
					}
				},
				"linkedServiceName": {
					"referenceName": "LS_SQL",
					"type": "LinkedServiceReference"
				}
			},
			{
				"name": "SP-ActivitySuccess07",
				"description": "DBT Processing successful ",
				"type": "SqlServerStoredProcedure",
				"dependsOn": [
					{
						"activity": "EP-DBT_Processing",
						"dependencyConditions": [
							"Succeeded"
						]
					}
				],
				"policy": {
					"timeout": "7.00:00:00",
					"retry": 5,
					"retryIntervalInSeconds": 30,
					"secureOutput": false,
					"secureInput": false
				},
				"userProperties": [],
				"typeProperties": {
					"storedProcedureName": "[dbo].[generic_activity_audit_log]",
					"storedProcedureParameters": {
						"activity_name": {
							"value": "EP_DBT_Processing",
							"type": "String"
						},
						"activity_status": {
							"value": {
								"value": "Successful",
								"type": "Expression"
							},
							"type": "String"
						},
						"application_name": {
							"value": {
								"value": "@activity('LU-Metadata').output.value[0].application_name",
								"type": "Expression"
							},
							"type": "String"
						},
						"dataset_name": {
							"value": {
								"value": "@activity('LU-Metadata').output.value[0].dataset_group",
								"type": "Expression"
							},
							"type": "String"
						},
						"pipeline_run_id": {
							"value": {
								"value": "@{pipeline().RunId}",
								"type": "Expression"
							},
							"type": "String"
						}
					}
				},
				"linkedServiceName": {
					"referenceName": "LS_SQL",
					"type": "LinkedServiceReference"
				}
			},
			{
				"name": "SP-ActivityFailed07",
				"description": "DBT processing activity failed",
				"type": "SqlServerStoredProcedure",
				"dependsOn": [
					{
						"activity": "EP-DBT_Processing",
						"dependencyConditions": [
							"Failed"
						]
					}
				],
				"policy": {
					"timeout": "7.00:00:00",
					"retry": 5,
					"retryIntervalInSeconds": 30,
					"secureOutput": false,
					"secureInput": false
				},
				"userProperties": [],
				"typeProperties": {
					"storedProcedureName": "[dbo].[generic_activity_error_audit_log]",
					"storedProcedureParameters": {
						"activity_name": {
							"value": "EP_DBT_Processing",
							"type": "String"
						},
						"activity_status": {
							"value": {
								"value": "Failed",
								"type": "Expression"
							},
							"type": "String"
						},
						"application_name": {
							"value": {
								"value": "@activity('LU-Metadata').output.value[0].application_name",
								"type": "Expression"
							},
							"type": "String"
						},
						"dataset_name": {
							"value": {
								"value": "@activity('LU-Metadata').output.value[0].dataset_group",
								"type": "Expression"
							},
							"type": "String"
						},
						"error_code": {
							"value": {
								"value": "N.A.",
								"type": "Expression"
							},
							"type": "String"
						},
						"error_detail": {
							"value": {
								"value": "N.A.",
								"type": "Expression"
							},
							"type": "String"
						},
						"pipeline_run_id": {
							"value": {
								"value": "@{pipeline().RunId}",
								"type": "Expression"
							},
							"type": "String"
						}
					}
				},
				"linkedServiceName": {
					"referenceName": "LS_SQL",
					"type": "LinkedServiceReference"
				}
			},
			{
				"name": "SP-ActivitySuccess01",
				"description": "LU- Metadata activity successful",
				"type": "SqlServerStoredProcedure",
				"dependsOn": [
					{
						"activity": "LU-Metadata",
						"dependencyConditions": [
							"Succeeded"
						]
					}
				],
				"policy": {
					"timeout": "7.00:00:00",
					"retry": 5,
					"retryIntervalInSeconds": 30,
					"secureOutput": false,
					"secureInput": false
				},
				"userProperties": [],
				"typeProperties": {
					"storedProcedureName": "[dbo].[generic_activity_audit_log]",
					"storedProcedureParameters": {
						"activity_name": {
							"value": "Metadata",
							"type": "String"
						},
						"activity_status": {
							"value": {
								"value": "Successful",
								"type": "Expression"
							},
							"type": "String"
						},
						"application_name": {
							"value": {
								"value": "@activity('LU-Metadata').output.value[0].application_name",
								"type": "Expression"
							},
							"type": "String"
						},
						"dataset_name": {
							"value": {
								"value": "@activity('LU-Metadata').output.value[0].dataset_group",
								"type": "Expression"
							},
							"type": "String"
						},
						"pipeline_run_id": {
							"value": {
								"value": "@{pipeline().RunId}",
								"type": "Expression"
							},
							"type": "String"
						}
					}
				},
				"linkedServiceName": {
					"referenceName": "LS_SQL",
					"type": "LinkedServiceReference"
				}
			},
			{
				"name": "SP-ActivityFailed01",
				"description": "To make entry of pipeline failure in audit log table in case triggers are not found",
				"type": "SqlServerStoredProcedure",
				"dependsOn": [
					{
						"activity": "LU-Metadata",
						"dependencyConditions": [
							"Failed"
						]
					}
				],
				"policy": {
					"timeout": "7.00:00:00",
					"retry": 5,
					"retryIntervalInSeconds": 30,
					"secureOutput": false,
					"secureInput": false
				},
				"userProperties": [],
				"typeProperties": {
					"storedProcedureName": "[dbo].[generic_activity_error_audit_log]",
					"storedProcedureParameters": {
						"activity_name": {
							"value": "Metadata",
							"type": "String"
						},
						"activity_status": {
							"value": {
								"value": "Failed",
								"type": "Expression"
							},
							"type": "String"
						},
						"application_name": {
							"value": {
								"value": "@activity('LU-Metadata').output.value[0].application_name",
								"type": "Expression"
							},
							"type": "String"
						},
						"dataset_name": {
							"value": {
								"value": "@activity('LU-Metadata').output.value[0].dataset_group",
								"type": "Expression"
							},
							"type": "String"
						},
						"error_code": {
							"value": {
								"value": "N.A.",
								"type": "Expression"
							},
							"type": "String"
						},
						"error_detail": {
							"value": {
								"value": "N.A.",
								"type": "Expression"
							},
							"type": "String"
						},
						"pipeline_run_id": {
							"value": {
								"value": "@{pipeline().RunId}",
								"type": "Expression"
							},
							"type": "String"
						}
					}
				},
				"linkedServiceName": {
					"referenceName": "LS_SQL",
					"type": "LinkedServiceReference"
				}
			},
			{
				"name": "SP-Pipelinesuccesful_master_pool_with_week_check",
				"description": "master pool pipeline successful ",
				"type": "SqlServerStoredProcedure",
				"dependsOn": [
					{
						"activity": "FE-CreateDBTTrigger",
						"dependencyConditions": [
							"Succeeded"
						]
					}
				],
				"policy": {
					"timeout": "7.00:00:00",
					"retry": 5,
					"retryIntervalInSeconds": 30,
					"secureOutput": false,
					"secureInput": false
				},
				"userProperties": [],
				"typeProperties": {
					"storedProcedureName": "[dbo].[generic_pipeline_audit_log]",
					"storedProcedureParameters": {
						"action_ind": {
							"value": "U",
							"type": "String"
						},
						"application_name": {
							"value": {
								"value": "@pipeline().parameters.ApplicationName",
								"type": "Expression"
							},
							"type": "String"
						},
						"dataset_name": {
							"value": {
								"value": "product_customer_master",
								"type": "Expression"
							},
							"type": "String"
						},
						"pipeline_name": {
							"value": {
								"value": "@{pipeline().Pipeline}",
								"type": "Expression"
							},
							"type": "String"
						},
						"pipeline_run_id": {
							"value": {
								"value": "@{pipeline().RunId}",
								"type": "Expression"
							},
							"type": "String"
						},
						"pipeline_status": {
							"value": "Successful",
							"type": "String"
						}
					}
				},
				"linkedServiceName": {
					"referenceName": "LS_SQL",
					"type": "LinkedServiceReference"
				}
			},
			{
				"name": "SP-EP-Snowflakeingestion-Failure",
				"description": "Snowflake ingestion failed and pipeline Failed",
				"type": "SqlServerStoredProcedure",
				"dependsOn": [
					{
						"activity": "EP-SnowflakeIngestion",
						"dependencyConditions": [
							"Failed"
						]
					}
				],
				"policy": {
					"timeout": "7.00:00:00",
					"retry": 5,
					"retryIntervalInSeconds": 30,
					"secureOutput": false,
					"secureInput": false
				},
				"userProperties": [],
				"typeProperties": {
					"storedProcedureName": "[dbo].[generic_pipeline_audit_log]",
					"storedProcedureParameters": {
						"action_ind": {
							"value": "U",
							"type": "String"
						},
						"application_name": {
							"value": {
								"value": "@activity('LU-Metadata').output.value[0].application_name",
								"type": "Expression"
							},
							"type": "String"
						},
						"dataset_name": {
							"value": {
								"value": "@activity('LU-Metadata').output.value[0].dataset_group",
								"type": "Expression"
							},
							"type": "String"
						},
						"pipeline_name": {
							"value": {
								"value": "@{pipeline().Pipeline}",
								"type": "Expression"
							},
							"type": "String"
						},
						"pipeline_run_id": {
							"value": {
								"value": "@{pipeline().RunId}",
								"type": "Expression"
							},
							"type": "String"
						},
						"pipeline_status": {
							"value": "Failed",
							"type": "String"
						}
					}
				},
				"linkedServiceName": {
					"referenceName": "LS_SQL",
					"type": "LinkedServiceReference"
				}
			},
			{
				"name": "SP-Pipelinefailure_ca_product_customer_master_pool_load",
				"description": "To make entry of pipeline failure in audit log table in case triggers are not found",
				"type": "SqlServerStoredProcedure",
				"dependsOn": [
					{
						"activity": "EP-DBT_Processing",
						"dependencyConditions": [
							"Failed"
						]
					}
				],
				"policy": {
					"timeout": "7.00:00:00",
					"retry": 5,
					"retryIntervalInSeconds": 30,
					"secureOutput": false,
					"secureInput": false
				},
				"userProperties": [],
				"typeProperties": {
					"storedProcedureName": "[dbo].[generic_pipeline_audit_log]",
					"storedProcedureParameters": {
						"action_ind": {
							"value": "U",
							"type": "String"
						},
						"application_name": {
							"value": {
								"value": "@pipeline().parameters.ApplicationName",
								"type": "Expression"
							},
							"type": "String"
						},
						"dataset_name": {
							"value": {
								"value": "product_customer_master",
								"type": "Expression"
							},
							"type": "String"
						},
						"pipeline_name": {
							"value": {
								"value": "@{pipeline().Pipeline}",
								"type": "Expression"
							},
							"type": "String"
						},
						"pipeline_run_id": {
							"value": {
								"value": "@{pipeline().RunId}",
								"type": "Expression"
							},
							"type": "String"
						},
						"pipeline_status": {
							"value": "Failed",
							"type": "String"
						}
					}
				},
				"linkedServiceName": {
					"referenceName": "LS_SQL",
					"type": "LinkedServiceReference"
				}
			},
			{
				"name": "FE-CreateDBTTrigger",
				"description": "Creating trigger ",
				"type": "ForEach",
				"dependsOn": [
					{
						"activity": "EP-DBT_Processing",
						"dependencyConditions": [
							"Succeeded"
						]
					}
				],
				"userProperties": [],
				"typeProperties": {
					"items": {
						"value": "@activity('LU-Metadata').output.value",
						"type": "Expression"
					},
					"activities": [
						{
							"name": "IF-Trigger",
							"type": "IfCondition",
							"dependsOn": [],
							"userProperties": [],
							"typeProperties": {
								"expression": {
									"value": "@and(not(empty(item().dbt_trigger_name)),greater(length(trim(item().dbt_trigger_name)), 0))",
									"type": "Expression"
								},
								"ifTrueActivities": [
									{
										"name": "SP-ActivitySuccess03",
										"type": "SqlServerStoredProcedure",
										"dependsOn": [
											{
												"activity": "CP-CreateDBT-Trigger",
												"dependencyConditions": [
													"Succeeded"
												]
											}
										],
										"policy": {
											"timeout": "7.00:00:00",
											"retry": 0,
											"retryIntervalInSeconds": 30,
											"secureOutput": false,
											"secureInput": false
										},
										"userProperties": [],
										"typeProperties": {
											"storedProcedureName": "[dbo].[generic_activity_audit_log]",
											"storedProcedureParameters": {
												"activity_name": {
													"value": {
														"value": "AF-TriggerLoad",
														"type": "Expression"
													},
													"type": "String"
												},
												"activity_status": {
													"value": {
														"value": "Successful",
														"type": "Expression"
													},
													"type": "String"
												},
												"application_name": {
													"value": {
														"value": "@{activity('LU-Metadata').output.value[0].application_name}",
														"type": "Expression"
													},
													"type": "String"
												},
												"dataset_name": {
													"value": {
														"value": "@{activity('LU-Metadata').output.value[0].dataset_group}",
														"type": "Expression"
													},
													"type": "String"
												},
												"pipeline_run_id": {
													"value": {
														"value": "@{pipeline().RunId}",
														"type": "Expression"
													},
													"type": "String"
												}
											}
										},
										"linkedServiceName": {
											"referenceName": "LS_SQL",
											"type": "LinkedServiceReference"
										}
									},
									{
										"name": "CP-CreateDBT-Trigger",
										"type": "Copy",
										"dependsOn": [],
										"policy": {
											"timeout": "7.00:00:00",
											"retry": 0,
											"retryIntervalInSeconds": 30,
											"secureOutput": false,
											"secureInput": false
										},
										"userProperties": [],
										"typeProperties": {
											"source": {
												"type": "SqlServerSource",
												"sqlReaderQuery": {
													"value": "select current_timestamp",
													"type": "Expression"
												},
												"queryTimeout": "02:00:00",
												"partitionOption": "None"
											},
											"sink": {
												"type": "DelimitedTextSink",
												"storeSettings": {
													"type": "AzureBlobFSWriteSettings"
												},
												"formatSettings": {
													"type": "DelimitedTextWriteSettings",
													"quoteAllText": true,
													"fileExtension": ".txt"
												}
											},
											"enableStaging": false,
											"translator": {
												"type": "TabularTranslator",
												"typeConversion": true,
												"typeConversionSettings": {
													"allowDataTruncation": true,
													"treatBooleanAsNumber": false
												}
											}
										},
										"inputs": [
											{
												"referenceName": "DS_KHCDE_GENERIC_MSSQL_Metadata",
												"type": "DatasetReference"
											}
										],
										"outputs": [
											{
												"referenceName": "DS_KHCDE_GENERIC_BLOB_CSV_FolderFile",
												"type": "DatasetReference",
												"parameters": {
													"container_name": {
														"value": "@{item().container_name}",
														"type": "Expression"
													},
													"blob_name": {
														"value": "@if(contains(item().dbt_trigger_name, '/'), substring(item().dbt_trigger_name, 0, lastIndexOf(item().dbt_trigger_name, '/')), 'sales/triggers')",
														"type": "Expression"
													},
													"file_name": {
														"value": "@if(contains(item().dbt_trigger_name, '/'), last(split(item().dbt_trigger_name, '/')), item().dbt_trigger_name)",
														"type": "Expression"
													},
													"field_delimiter": {
														"value": ",",
														"type": "Expression"
													}
												}
											}
										]
									}
								]
							}
						}
					]
				}
			},
			{
				"name": "SP-Pipelinefailure_ca_product_customer_master_pool",
				"description": "DBT Processing failed and exiting the pipeline",
				"type": "SqlServerStoredProcedure",
				"dependsOn": [
					{
						"activity": "FE-CreateDBTTrigger",
						"dependencyConditions": [
							"Failed"
						]
					}
				],
				"policy": {
					"timeout": "7.00:00:00",
					"retry": 5,
					"retryIntervalInSeconds": 30,
					"secureOutput": false,
					"secureInput": false
				},
				"userProperties": [],
				"typeProperties": {
					"storedProcedureName": "[dbo].[generic_pipeline_audit_log]",
					"storedProcedureParameters": {
						"action_ind": {
							"value": "U",
							"type": "String"
						},
						"application_name": {
							"value": {
								"value": "@pipeline().parameters.ApplicationName",
								"type": "Expression"
							},
							"type": "String"
						},
						"dataset_name": {
							"value": {
								"value": "product_customer_master",
								"type": "Expression"
							},
							"type": "String"
						},
						"pipeline_name": {
							"value": {
								"value": "@{pipeline().Pipeline}",
								"type": "Expression"
							},
							"type": "String"
						},
						"pipeline_run_id": {
							"value": {
								"value": "@{pipeline().RunId}",
								"type": "Expression"
							},
							"type": "String"
						},
						"pipeline_status": {
							"value": "Failed",
							"type": "String"
						}
					}
				},
				"linkedServiceName": {
					"referenceName": "LS_SQL",
					"type": "LinkedServiceReference"
				}
			},
			{
				"name": "SP-ActivitySuccess08",
				"description": "DBT Processing Successful",
				"type": "SqlServerStoredProcedure",
				"dependsOn": [
					{
						"activity": "FE-CreateDBTTrigger",
						"dependencyConditions": [
							"Succeeded"
						]
					}
				],
				"policy": {
					"timeout": "7.00:00:00",
					"retry": 5,
					"retryIntervalInSeconds": 30,
					"secureOutput": false,
					"secureInput": false
				},
				"userProperties": [],
				"typeProperties": {
					"storedProcedureName": "[dbo].[generic_activity_audit_log]",
					"storedProcedureParameters": {
						"activity_name": {
							"value": "EP_DBT_Processing",
							"type": "String"
						},
						"activity_status": {
							"value": {
								"value": "Successful",
								"type": "Expression"
							},
							"type": "String"
						},
						"application_name": {
							"value": {
								"value": "@activity('LU-Metadata').output.value[0].application_name",
								"type": "Expression"
							},
							"type": "String"
						},
						"dataset_name": {
							"value": {
								"value": "@activity('LU-Metadata').output.value[0].dataset_group",
								"type": "Expression"
							},
							"type": "String"
						},
						"pipeline_run_id": {
							"value": {
								"value": "@{pipeline().RunId}",
								"type": "Expression"
							},
							"type": "String"
						}
					}
				},
				"linkedServiceName": {
					"referenceName": "LS_SQL",
					"type": "LinkedServiceReference"
				}
			},
			{
				"name": "SP-ActivityFailed08",
				"description": "DBT processing activity failed",
				"type": "SqlServerStoredProcedure",
				"dependsOn": [
					{
						"activity": "FE-CreateDBTTrigger",
						"dependencyConditions": [
							"Failed"
						]
					}
				],
				"policy": {
					"timeout": "7.00:00:00",
					"retry": 5,
					"retryIntervalInSeconds": 30,
					"secureOutput": false,
					"secureInput": false
				},
				"userProperties": [],
				"typeProperties": {
					"storedProcedureName": "[dbo].[generic_activity_error_audit_log]",
					"storedProcedureParameters": {
						"activity_name": {
							"value": "EP_DBT_Processing",
							"type": "String"
						},
						"activity_status": {
							"value": {
								"value": "Failed",
								"type": "Expression"
							},
							"type": "String"
						},
						"application_name": {
							"value": {
								"value": "@activity('LU-Metadata').output.value[0].application_name",
								"type": "Expression"
							},
							"type": "String"
						},
						"dataset_name": {
							"value": {
								"value": "@activity('LU-Metadata').output.value[0].dataset_group",
								"type": "Expression"
							},
							"type": "String"
						},
						"error_code": {
							"value": {
								"value": "N.A.",
								"type": "Expression"
							},
							"type": "String"
						},
						"error_detail": {
							"value": {
								"value": "N.A.",
								"type": "Expression"
							},
							"type": "String"
						},
						"pipeline_run_id": {
							"value": {
								"value": "@{pipeline().RunId}",
								"type": "Expression"
							},
							"type": "String"
						}
					}
				},
				"linkedServiceName": {
					"referenceName": "LS_SQL",
					"type": "LinkedServiceReference"
				}
			},
			{
				"name": "LU-Get_trigger_value",
				"description": "This will get the row from the orchestration metadata table for the trigger dataset",
				"type": "Lookup",
				"dependsOn": [
					{
						"activity": "SP-PipelineStart_Snowflake",
						"dependencyConditions": [
							"Succeeded"
						]
					}
				],
				"policy": {
					"timeout": "7.00:00:00",
					"retry": 5,
					"retryIntervalInSeconds": 30,
					"secureOutput": false,
					"secureInput": false
				},
				"userProperties": [],
				"typeProperties": {
					"source": {
						"type": "SqlServerSource",
						"sqlReaderQuery": {
							"value": "select * from khc_orchestration_metadata where application_name like '%@{pipeline().parameters.ApplicationName}%' \nand adf_trigger_name = '@{replace(pipeline().parameters.adf_trigger_name,'_trigger.txt','')}' and data_level = 1 and active_ind = 'y';",
							"type": "Expression"
						},
						"queryTimeout": "02:00:00",
						"partitionOption": "None"
					},
					"dataset": {
						"referenceName": "DS_KHCDE_GENERIC_MSSQL_Metadata",
						"type": "DatasetReference"
					},
					"firstRowOnly": false
				}
			},
			{
				"name": "SP-ActivitySuccess02",
				"description": "Get trigger value activity successful",
				"type": "SqlServerStoredProcedure",
				"dependsOn": [
					{
						"activity": "LU-Get_trigger_value",
						"dependencyConditions": [
							"Succeeded"
						]
					}
				],
				"policy": {
					"timeout": "7.00:00:00",
					"retry": 5,
					"retryIntervalInSeconds": 30,
					"secureOutput": false,
					"secureInput": false
				},
				"userProperties": [],
				"typeProperties": {
					"storedProcedureName": "[dbo].[generic_activity_audit_log]",
					"storedProcedureParameters": {
						"activity_name": {
							"value": {
								"value": "LU-Get_trigger_value",
								"type": "Expression"
							},
							"type": "String"
						},
						"activity_status": {
							"value": {
								"value": "Successful",
								"type": "Expression"
							},
							"type": "String"
						},
						"application_name": {
							"value": {
								"value": "@activity('LU-Get_trigger_value').output.value[0].application_name",
								"type": "Expression"
							},
							"type": "String"
						},
						"dataset_name": {
							"value": {
								"value": "@activity('LU-Get_trigger_value').output.value[0].dataset_group",
								"type": "Expression"
							},
							"type": "String"
						},
						"pipeline_run_id": {
							"value": {
								"value": "@{pipeline().RunId}",
								"type": "Expression"
							},
							"type": "String"
						}
					}
				},
				"linkedServiceName": {
					"referenceName": "LS_SQL",
					"type": "LinkedServiceReference"
				}
			},
			{
				"name": "SP-ActivityFailed02",
				"description": "Get trigger value activity failed",
				"type": "SqlServerStoredProcedure",
				"dependsOn": [
					{
						"activity": "LU-Get_trigger_value",
						"dependencyConditions": [
							"Failed"
						]
					}
				],
				"policy": {
					"timeout": "7.00:00:00",
					"retry": 5,
					"retryIntervalInSeconds": 30,
					"secureOutput": false,
					"secureInput": false
				},
				"userProperties": [],
				"typeProperties": {
					"storedProcedureName": "[dbo].[generic_activity_error_audit_log]",
					"storedProcedureParameters": {
						"activity_name": {
							"value": {
								"value": "LU-Get_trigger_value",
								"type": "Expression"
							},
							"type": "String"
						},
						"activity_status": {
							"value": {
								"value": "Failed",
								"type": "Expression"
							},
							"type": "String"
						},
						"application_name": {
							"value": {
								"value": "@activity('LU-Get_trigger_value').output.value[0].application_name",
								"type": "Expression"
							},
							"type": "String"
						},
						"dataset_name": {
							"value": {
								"value": "@activity('LU-Get_trigger_value').output.value[0].dataset_group",
								"type": "Expression"
							},
							"type": "String"
						},
						"error_code": {
							"value": {
								"value": "N.A.",
								"type": "Expression"
							},
							"type": "String"
						},
						"error_detail": {
							"value": {
								"value": "N.A.",
								"type": "Expression"
							},
							"type": "String"
						},
						"pipeline_run_id": {
							"value": {
								"value": "@{pipeline().RunId}",
								"type": "Expression"
							},
							"type": "String"
						}
					}
				},
				"linkedServiceName": {
					"referenceName": "LS_SQL",
					"type": "LinkedServiceReference"
				}
			},
			{
				"name": "SP-ActivitySuccess04",
				"description": "Trigger file deleted successfully ",
				"type": "SqlServerStoredProcedure",
				"dependsOn": [
					{
						"activity": "If Condition- Trigger Availability",
						"dependencyConditions": [
							"Succeeded"
						]
					}
				],
				"policy": {
					"timeout": "7.00:00:00",
					"retry": 5,
					"retryIntervalInSeconds": 30,
					"secureOutput": false,
					"secureInput": false
				},
				"userProperties": [],
				"typeProperties": {
					"storedProcedureName": "[dbo].[generic_activity_audit_log]",
					"storedProcedureParameters": {
						"activity_name": {
							"value": {
								"value": "DL-Trigger",
								"type": "Expression"
							},
							"type": "String"
						},
						"activity_status": {
							"value": {
								"value": "Success",
								"type": "Expression"
							},
							"type": "String"
						},
						"application_name": {
							"value": {
								"value": "@activity('LU-Get_trigger_value').output.value[0].application_name",
								"type": "Expression"
							},
							"type": "String"
						},
						"dataset_name": {
							"value": {
								"value": "@activity('LU-Get_trigger_value').output.value[0].dataset_group",
								"type": "Expression"
							},
							"type": "String"
						},
						"pipeline_run_id": {
							"value": {
								"value": "@{pipeline().RunId}",
								"type": "Expression"
							},
							"type": "String"
						}
					}
				},
				"linkedServiceName": {
					"referenceName": "LS_SQL",
					"type": "LinkedServiceReference"
				}
			},
			{
				"name": "SuccessEmailSender",
				"description": "Email notification for success of pipeline",
				"type": "WebActivity",
				"dependsOn": [
					{
						"activity": "SP-Pipelinesuccesful_master_pool_with_week_check",
						"dependencyConditions": [
							"Succeeded"
						]
					}
				],
				"policy": {
					"timeout": "7.00:00:00",
					"retry": 5,
					"retryIntervalInSeconds": 30,
					"secureOutput": false,
					"secureInput": false
				},
				"userProperties": [],
				"typeProperties": {
					"url": {
						"value": "@pipeline().globalParameters.la_khcde_generic_email_url",
						"type": "Expression"
					},
					"method": "POST",
					"body": {
						"value": "{ \n\"to_email\":\"@{variables('to_emails')}\", \n\"subject\":\"Ca product customer Load process Successful\", \n\"body\": \"Data Load process has been completed Successfully for application @{pipeline().parameters.ApplicationName}. The pipelinename is @{pipeline().Pipeline}. The pipelineid is @{pipeline().RunId}. The Dataset name is @{activity('LU-Metadata').output.value[0].dataset_group}\",\n\"importance\": \"Low\"\n}\n",
						"type": "Expression"
					}
				}
			},
			{
				"name": "FailureEmailSender",
				"description": "Email notification for failure of pipeline",
				"type": "WebActivity",
				"dependsOn": [
					{
						"activity": "SP-Pipelinefailure_ca_product_customer_master_pool",
						"dependencyConditions": [
							"Succeeded"
						]
					}
				],
				"policy": {
					"timeout": "7.00:00:00",
					"retry": 5,
					"retryIntervalInSeconds": 30,
					"secureOutput": false,
					"secureInput": false
				},
				"userProperties": [],
				"typeProperties": {
					"url": {
						"value": "@pipeline().globalParameters.la_khcde_generic_email_url",
						"type": "Expression"
					},
					"method": "POST",
					"body": {
						"value": "{\n\"to_email\":\"@{variables('to_emails')}\", \n\"subject\":\"Ca Product Customer DBT load Process failed\",\n\"body\": \"The application name is @{pipeline().parameters.ApplicationName}. The pipelinename is @{pipeline().Pipeline}. The pipelineid is @{pipeline().RunId}. The Dataset name is @{activity('LU-Metadata').output.value[0].dataset_group}\",\n\"importance\": \"High\"\n}\n",
						"type": "Expression"
					}
				}
			},
			{
				"name": "FailureEmailSender_Snowflake",
				"description": "Email notification for failure of snowflake process",
				"type": "WebActivity",
				"dependsOn": [
					{
						"activity": "SP-EP-Snowflakeingestion-Failure",
						"dependencyConditions": [
							"Succeeded"
						]
					}
				],
				"policy": {
					"timeout": "7.00:00:00",
					"retry": 5,
					"retryIntervalInSeconds": 30,
					"secureOutput": false,
					"secureInput": false
				},
				"userProperties": [],
				"typeProperties": {
					"url": {
						"value": "@pipeline().globalParameters.la_khcde_generic_email_url",
						"type": "Expression"
					},
					"method": "POST",
					"body": {
						"value": "{\n\"to_email\":\"@{variables('to_emails')}\",\n\"subject\":\" Ca Product Customer Snowflake ingestion load Process failed\",\n\"body\": \"The application name is @{pipeline().parameters.ApplicationName}. The pipelinename is @{pipeline().Pipeline}. The pipelineid is @{pipeline().RunId}. The Dataset name is @{activity('LU-Metadata').output.value[0].dataset_group}\",\n\"importance\": \"High\"\n}",
						"type": "Expression"
					}
				}
			},
			{
				"name": "If Condition- Trigger Availability",
				"description": "Checking whether the triggers are present.",
				"type": "IfCondition",
				"dependsOn": [
					{
						"activity": "LU-Get_trigger_value",
						"dependencyConditions": [
							"Succeeded"
						]
					}
				],
				"userProperties": [],
				"typeProperties": {
					"expression": {
						"value": "@and(not(equals(coalesce(trim(activity('LU-Get_trigger_value').output.value[0].blob_trigger_name), ''), '')),not(equals(coalesce(trim(activity('LU-Get_trigger_value').output.value[0].container_name), ''), '')))",
						"type": "Expression"
					},
					"ifFalseActivities": [
						{
							"name": "CP-ReraiseError_Inner",
							"type": "Copy",
							"dependsOn": [],
							"policy": {
								"timeout": "7.00:00:00",
								"retry": 0,
								"retryIntervalInSeconds": 30,
								"secureOutput": false,
								"secureInput": false
							},
							"userProperties": [],
							"typeProperties": {
								"source": {
									"type": "BinarySource",
									"storeSettings": {
										"type": "AzureBlobFSReadSettings",
										"recursive": true
									},
									"formatSettings": {
										"type": "BinaryReadSettings"
									}
								},
								"sink": {
									"type": "BinarySink",
									"storeSettings": {
										"type": "AzureBlobFSWriteSettings"
									}
								},
								"enableStaging": false
							},
							"inputs": [
								{
									"referenceName": "DS_KHCDE_GENERIC_BLOB_BINARY_Folder",
									"type": "DatasetReference",
									"parameters": {
										"container_name": {
											"value": "doesNotExist_Input",
											"type": "Expression"
										},
										"blob_name": {
											"value": "doesNotExist_Input",
											"type": "Expression"
										}
									}
								}
							],
							"outputs": [
								{
									"referenceName": "DS_KHCDE_GENERIC_BLOB_BINARY_Folder",
									"type": "DatasetReference",
									"parameters": {
										"container_name": {
											"value": "doesNotExist_Input",
											"type": "Expression"
										},
										"blob_name": {
											"value": "doesNotExist_Input",
											"type": "Expression"
										}
									}
								}
							]
						}
					],
					"ifTrueActivities": [
						{
							"name": "DL-Trigger",
							"type": "Delete",
							"dependsOn": [],
							"policy": {
								"timeout": "7.00:00:00",
								"retry": 0,
								"retryIntervalInSeconds": 30,
								"secureOutput": false,
								"secureInput": false
							},
							"userProperties": [],
							"typeProperties": {
								"dataset": {
									"referenceName": "DS_KHCDE_ADLS_Blob",
									"type": "DatasetReference",
									"parameters": {
										"container": {
											"value": "@activity('LU-Get_trigger_value').output.value[0].container_name",
											"type": "Expression"
										},
										"stage_path": {
											"value": "@activity('LU-Get_trigger_value').output.value[0].blob_trigger_name",
											"type": "Expression"
										}
									}
								},
								"enableLogging": false,
								"storeSettings": {
									"type": "AzureBlobFSReadSettings",
									"recursive": true,
									"wildcardFileName": {
										"value": "@{concat('*',activity('LU-Get_trigger_value').output.value[0].application_name,'*')}",
										"type": "Expression"
									}
								}
							}
						}
					]
				}
			}
		],
		"parameters": {
			"ApplicationName": {
				"type": "string",
				"defaultValue": "ca_product_customer"
			},
			"adf_trigger_name": {
				"type": "string",
				"defaultValue": "@trigger().outputs.body.fileName"
			}
		},
		"variables": {
			"exit": {
				"type": "String",
				"defaultValue": "N"
			},
			"adf_trigger_name": {
				"type": "String"
			},
			"to_emails": {
				"type": "String",
				"defaultValue": "KHC_CANADA_DE@kraftheinz.com"
			}
		},
		"folder": {
			"name": "CA_Product_Customer"
		},
		"annotations": []
	},
	"type": "Microsoft.DataFactory/factories/pipelines"
}