{
	"name": "TRG_KHCDE_APAC_PNG_INV_NINEPM_DAILY",
	"properties": {
		"description": "NINE PM daily trigger for PNG entity",
		"annotations": [],
		"runtimeState": "Started",
		"pipelines": [
			{
				"pipelineReference": {
					"referenceName": "PL_KHCDE_APAC_MASTER_EXTRACT",
					"type": "PipelineReference"
				},
				"parameters": {
					"application_name": "sales_management_international",
					"adf_trigger_name": "TRG_KHCDE_APAC_PNG_INV_NINEPM_DAILY"
				}
			}
		],
		"type": "ScheduleTrigger",
		"typeProperties": {
			"recurrence": {
				"frequency": "Day",
				"interval": 1,
				"startTime": "2021-09-21T07:38:00Z",
				"timeZone": "UTC",
				"schedule": {
					"minutes": [
						0
					],
					"hours": [
						21
					]
				}
			}
		}
	}
}