{
	"name": "TRG_KHCDE_APAC_CN_DF_LOGISTICS_TWICE_DAILY",
	"properties": {
		"description": "Trigger the pipeline to load the China data foundation table data at 4:15 a.m. 8:15 a.m.",
		"annotations": [],
		"runtimeState": "Started",
		"pipelines": [
			{
				"pipelineReference": {
					"referenceName": "PL_KHCDE_APAC_MASTER_EXTRACT",
					"type": "PipelineReference"
				},
				"parameters": {
					"application_name": "khc_logistics",
					"adf_trigger_name": "TRG_KHCDE_APAC_CN_DF_LOGISTICS_TWICE_DAILY"
				}
			}
		],
		"type": "ScheduleTrigger",
		"typeProperties": {
			"recurrence": {
				"frequency": "Day",
				"interval": 1,
				"startTime": "2022-02-15T06:44:00Z",
				"timeZone": "UTC",
				"schedule": {
					"minutes": [
						15
					],
					"hours": [
						4,
						8
					]
				}
			}
		}
	}
}