{
	"name": "TRG_KHCDE_RAPID7_POSTGRE_DAILY",
	"properties": {
		"description": "Trigger created to fetch the data from Postgres at 6pm CST daily.",
		"annotations": [],
		"runtimeState": "Started",
		"pipelines": [
			{
				"pipelineReference": {
					"referenceName": "PL_KHCDE_RAPID7_MASTER_POOL_LOAD",
					"type": "PipelineReference"
				},
				"parameters": {
					"application_name": "rapid7",
					"dataset_group": "rapid7_data"
				}
			}
		],
		"type": "ScheduleTrigger",
		"typeProperties": {
			"recurrence": {
				"frequency": "Day",
				"interval": 1,
				"startTime": "2022-02-14T16:26:00",
				"timeZone": "Central Standard Time",
				"schedule": {
					"minutes": [
						0
					],
					"hours": [
						18
					]
				}
			}
		}
	}
}