{
	"name": "PL_KHCDE_MARKET_AMOBEE_MASTER_LOAD",
	"properties": {
		"description": "Master Pipeline for AMOBEE, used to load data from RAW files to Snowflake and execute DBT Transformations",
		"activities": [
			{
				"name": "LU-MetaData-LookUp",
				"description": "Amobee meta data look up activity.\nChecks for amobee meta data from khc_orchestration_metadata table.",
				"type": "Lookup",
				"dependsOn": [
					{
						"activity": "SP-PipelineStart_Snowflake",
						"dependencyConditions": [
							"Succeeded"
						]
					}
				],
				"policy": {
					"timeout": "7.00:00:00",
					"retry": 0,
					"retryIntervalInSeconds": 30,
					"secureOutput": false,
					"secureInput": false
				},
				"userProperties": [],
				"typeProperties": {
					"source": {
						"type": "SqlServerSource",
						"sqlReaderQuery": {
							"value": "select * from khc_orchestration_metadata where application_name='amobee' and adf_trigger_name ='@{pipeline().parameters.trigger_file_name}' and active_ind='y'",
							"type": "Expression"
						},
						"queryTimeout": "02:00:00",
						"partitionOption": "None"
					},
					"dataset": {
						"referenceName": "DS_KHCDE_GENERIC_MSSQL_Metadata",
						"type": "DatasetReference"
					},
					"firstRowOnly": false
				}
			},
			{
				"name": "EP-sfk_ingestion",
				"description": "This activity invokes generic sfk ingestion pipeline for data ingestion to snowflake.",
				"type": "ExecutePipeline",
				"dependsOn": [
					{
						"activity": "Delete_After_Condition_Check",
						"dependencyConditions": [
							"Succeeded"
						]
					}
				],
				"userProperties": [],
				"typeProperties": {
					"pipeline": {
						"referenceName": "PL_KHCDE_GENERIC_SnowflakeIngestion",
						"type": "PipelineReference"
					},
					"waitOnCompletion": true,
					"parameters": {
						"ApplicationName": {
							"value": "@pipeline().parameters.application_name",
							"type": "Expression"
						},
						"DatasetGroup": {
							"value": "@activity('LU-MetaData-LookUp').output.value[0].dataset_group",
							"type": "Expression"
						},
						"ParameterJson": {
							"value": "@activity('LU-MetaData-LookUp').output.value[0].parameter_json",
							"type": "Expression"
						}
					}
				}
			},
			{
				"name": "LU_metadata_lookup_Audit_Detail_Success",
				"description": "This activity logs success of LU-MetaData-LookUp activity in khc_audit_log_detail table.",
				"type": "SqlServerStoredProcedure",
				"dependsOn": [
					{
						"activity": "LU-MetaData-LookUp",
						"dependencyConditions": [
							"Succeeded"
						]
					}
				],
				"policy": {
					"timeout": "7.00:00:00",
					"retry": 0,
					"retryIntervalInSeconds": 30,
					"secureOutput": false,
					"secureInput": false
				},
				"userProperties": [],
				"typeProperties": {
					"storedProcedureName": "[dbo].[generic_activity_audit_log]",
					"storedProcedureParameters": {
						"activity_name": {
							"value": "LU-MetaData-LookUp",
							"type": "String"
						},
						"activity_status": {
							"value": {
								"value": "Successful",
								"type": "Expression"
							},
							"type": "String"
						},
						"application_name": {
							"value": {
								"value": "@activity('LU-MetaData-LookUp').output.value[0].application_name",
								"type": "Expression"
							},
							"type": "String"
						},
						"dataset_name": {
							"value": {
								"value": "@activity('LU-MetaData-LookUp').output.value[0].dataset_name",
								"type": "Expression"
							},
							"type": "String"
						},
						"pipeline_run_id": {
							"value": {
								"value": "@pipeline().RunId",
								"type": "Expression"
							},
							"type": "String"
						}
					}
				},
				"linkedServiceName": {
					"referenceName": "LS_SQL",
					"type": "LinkedServiceReference"
				}
			},
			{
				"name": "LU_MetaData_LookUp_Audit_detail_failure",
				"description": "This activity logs failure of LU-MetaData-LookUpa activity in khc_audit_log_detail table and failure of pipeline in  khc_audit_log table.",
				"type": "SqlServerStoredProcedure",
				"dependsOn": [
					{
						"activity": "LU-MetaData-LookUp",
						"dependencyConditions": [
							"Failed"
						]
					}
				],
				"policy": {
					"timeout": "7.00:00:00",
					"retry": 0,
					"retryIntervalInSeconds": 30,
					"secureOutput": false,
					"secureInput": false
				},
				"userProperties": [],
				"typeProperties": {
					"storedProcedureName": "[dbo].[generic_activity_error_audit_log]",
					"storedProcedureParameters": {
						"action_ind": {
							"value": "U",
							"type": "String"
						},
						"activity_name": {
							"value": "LU-MetaData-LookUp",
							"type": "String"
						},
						"activity_status": {
							"value": "Failed",
							"type": "String"
						},
						"application_name": {
							"value": {
								"value": "@pipeline().parameters.application_name",
								"type": "Expression"
							},
							"type": "String"
						},
						"dataset_name": {
							"value": {
								"value": "@activity('LU-MetaData-LookUp').output.value[0].dataset_name",
								"type": "Expression"
							},
							"type": "String"
						},
						"error_code": {
							"value": "N.A.",
							"type": "String"
						},
						"error_detail": {
							"value": "N.A.",
							"type": "String"
						},
						"pipeline_run_id": {
							"value": {
								"value": "@pipeline().RunId",
								"type": "Expression"
							},
							"type": "String"
						},
						"pipeline_status": {
							"value": "Failed",
							"type": "String"
						},
						"skip_pipeline_audit_update": {
							"value": "N",
							"type": "String"
						}
					}
				},
				"linkedServiceName": {
					"referenceName": "LS_SQL",
					"type": "LinkedServiceReference"
				}
			},
			{
				"name": "EP_SFK_Ingestion_Audit_Detail_Success",
				"description": "This activity logs success of EP_SFK_Ingestion activity in khc_audit_log_detail table.",
				"type": "SqlServerStoredProcedure",
				"dependsOn": [
					{
						"activity": "EP-sfk_ingestion",
						"dependencyConditions": [
							"Succeeded"
						]
					}
				],
				"policy": {
					"timeout": "7.00:00:00",
					"retry": 0,
					"retryIntervalInSeconds": 30,
					"secureOutput": false,
					"secureInput": false
				},
				"userProperties": [],
				"typeProperties": {
					"storedProcedureName": "[dbo].[generic_activity_audit_log]",
					"storedProcedureParameters": {
						"activity_name": {
							"value": "EP-sfk_ingestion",
							"type": "String"
						},
						"activity_status": {
							"value": {
								"value": "Successful",
								"type": "Expression"
							},
							"type": "String"
						},
						"application_name": {
							"value": "amobee",
							"type": "String"
						},
						"dataset_name": {
							"value": {
								"value": "@activity('LU-MetaData-LookUp').output.value[0].dataset_name",
								"type": "Expression"
							},
							"type": "String"
						},
						"pipeline_run_id": {
							"value": {
								"value": "@pipeline().RunId",
								"type": "Expression"
							},
							"type": "String"
						}
					}
				},
				"linkedServiceName": {
					"referenceName": "LS_SQL",
					"type": "LinkedServiceReference"
				}
			},
			{
				"name": "EP_SFK_Ingestion_Audit_Detail_failure",
				"description": "This activity logs failure of EP_SFK_Ingestion activity in khc_audit_log_detail table and failure of pipeline in  khc_audit_log table.",
				"type": "SqlServerStoredProcedure",
				"dependsOn": [
					{
						"activity": "EP-sfk_ingestion",
						"dependencyConditions": [
							"Failed"
						]
					}
				],
				"policy": {
					"timeout": "7.00:00:00",
					"retry": 0,
					"retryIntervalInSeconds": 30,
					"secureOutput": false,
					"secureInput": false
				},
				"userProperties": [],
				"typeProperties": {
					"storedProcedureName": "[dbo].[generic_activity_error_audit_log]",
					"storedProcedureParameters": {
						"action_ind": {
							"value": "U",
							"type": "String"
						},
						"activity_name": {
							"value": "EP-sfk_ingestion",
							"type": "String"
						},
						"activity_status": {
							"value": "Failed",
							"type": "String"
						},
						"application_name": {
							"value": "amobee",
							"type": "String"
						},
						"dataset_name": {
							"value": {
								"value": "@activity('LU-MetaData-LookUp').output.value[0].dataset_name",
								"type": "Expression"
							},
							"type": "String"
						},
						"error_code": {
							"value": "N.A.",
							"type": "String"
						},
						"error_detail": {
							"value": "N.A.",
							"type": "String"
						},
						"pipeline_run_id": {
							"value": {
								"value": "@pipeline().RunId",
								"type": "Expression"
							},
							"type": "String"
						},
						"pipeline_status": {
							"value": "Failed",
							"type": "String"
						},
						"skip_pipeline_audit_update": {
							"value": "N",
							"type": "String"
						}
					}
				},
				"linkedServiceName": {
					"referenceName": "LS_SQL",
					"type": "LinkedServiceReference"
				}
			},
			{
				"name": "EP_DBT_processing",
				"description": "This activity invokes generic DBT processing pipeline for amobee data feeds.",
				"type": "ExecutePipeline",
				"dependsOn": [
					{
						"activity": "EP-sfk_ingestion",
						"dependencyConditions": [
							"Succeeded"
						]
					}
				],
				"userProperties": [],
				"typeProperties": {
					"pipeline": {
						"referenceName": "PL_KHCDE_GENERIC_DBTProcessing",
						"type": "PipelineReference"
					},
					"waitOnCompletion": true,
					"parameters": {
						"ApplicationName": {
							"value": "@activity('LU-MetaData-LookUp').output.value[0].application_name",
							"type": "Expression"
						},
						"DatasetGroup": {
							"value": "@activity('LU-MetaData-LookUp').output.value[0].dataset_group",
							"type": "Expression"
						},
						"ParameterJson": {
							"value": "@activity('LU-MetaData-LookUp').output.value[0].parameter_json",
							"type": "Expression"
						}
					}
				}
			},
			{
				"name": "EP_DBT_processing_Audit_Detail_Success",
				"description": "This activity logs success of EP_DBT_processing activity in khc_audit_log_detail table.",
				"type": "SqlServerStoredProcedure",
				"dependsOn": [
					{
						"activity": "EP_DBT_processing",
						"dependencyConditions": [
							"Succeeded"
						]
					}
				],
				"policy": {
					"timeout": "7.00:00:00",
					"retry": 0,
					"retryIntervalInSeconds": 30,
					"secureOutput": false,
					"secureInput": false
				},
				"userProperties": [],
				"typeProperties": {
					"storedProcedureName": "[dbo].[generic_activity_audit_log]",
					"storedProcedureParameters": {
						"activity_name": {
							"value": "EP_DBT_processing",
							"type": "String"
						},
						"activity_status": {
							"value": {
								"value": "Successful",
								"type": "Expression"
							},
							"type": "String"
						},
						"application_name": {
							"value": "amobee",
							"type": "String"
						},
						"dataset_name": {
							"value": {
								"value": "@activity('LU-MetaData-LookUp').output.value[0].dataset_name",
								"type": "Expression"
							},
							"type": "String"
						},
						"pipeline_run_id": {
							"value": {
								"value": "@pipeline().RunId",
								"type": "Expression"
							},
							"type": "String"
						}
					}
				},
				"linkedServiceName": {
					"referenceName": "LS_SQL",
					"type": "LinkedServiceReference"
				}
			},
			{
				"name": "EP_DBT_processing_Audit_Detail_failure",
				"description": "This activity logs failure of EP_DBT_processing activity in khc_audit_log_detail table and failure of pipeline in  khc_audit_log table.",
				"type": "SqlServerStoredProcedure",
				"dependsOn": [
					{
						"activity": "EP_DBT_processing",
						"dependencyConditions": [
							"Failed"
						]
					}
				],
				"policy": {
					"timeout": "7.00:00:00",
					"retry": 0,
					"retryIntervalInSeconds": 30,
					"secureOutput": false,
					"secureInput": false
				},
				"userProperties": [],
				"typeProperties": {
					"storedProcedureName": "[dbo].[generic_activity_error_audit_log]",
					"storedProcedureParameters": {
						"action_ind": {
							"value": "U",
							"type": "String"
						},
						"activity_name": {
							"value": "EP_DBT_processing",
							"type": "String"
						},
						"activity_status": {
							"value": "Failed",
							"type": "String"
						},
						"application_name": {
							"value": "amobee",
							"type": "String"
						},
						"dataset_name": {
							"value": {
								"value": "@activity('LU-MetaData-LookUp').output.value[0].dataset_name",
								"type": "Expression"
							},
							"type": "String"
						},
						"error_code": {
							"value": "N.A.",
							"type": "String"
						},
						"error_detail": {
							"value": "N.A.",
							"type": "String"
						},
						"pipeline_run_id": {
							"value": {
								"value": "@pipeline().RunId",
								"type": "Expression"
							},
							"type": "String"
						},
						"pipeline_status": {
							"value": "Failed",
							"type": "String"
						},
						"skip_pipeline_audit_update": {
							"value": "N",
							"type": "String"
						}
					}
				},
				"linkedServiceName": {
					"referenceName": "LS_SQL",
					"type": "LinkedServiceReference"
				}
			},
			{
				"name": "DL-trigger_Success",
				"description": "Activity to log the success status of trigger file deletion",
				"type": "SqlServerStoredProcedure",
				"dependsOn": [
					{
						"activity": "Delete_After_Condition_Check",
						"dependencyConditions": [
							"Succeeded"
						]
					}
				],
				"policy": {
					"timeout": "7.00:00:00",
					"retry": 0,
					"retryIntervalInSeconds": 30,
					"secureOutput": false,
					"secureInput": false
				},
				"userProperties": [],
				"typeProperties": {
					"storedProcedureName": "[dbo].[generic_activity_audit_log]",
					"storedProcedureParameters": {
						"activity_name": {
							"value": {
								"value": "DL-Trigger",
								"type": "Expression"
							},
							"type": "String"
						},
						"activity_status": {
							"value": {
								"value": "Success",
								"type": "Expression"
							},
							"type": "String"
						},
						"application_name": {
							"value": {
								"value": "@activity('LU-Metadata-LookUp').output.value[0].application_name",
								"type": "Expression"
							},
							"type": "String"
						},
						"dataset_name": {
							"value": {
								"value": "@activity('LU-Metadata-LookUp').output.value[0].dataset_name",
								"type": "Expression"
							},
							"type": "String"
						},
						"pipeline_run_id": {
							"value": {
								"value": "@{pipeline().RunId}",
								"type": "Expression"
							},
							"type": "String"
						}
					}
				},
				"linkedServiceName": {
					"referenceName": "LS_SQL",
					"type": "LinkedServiceReference"
				}
			},
			{
				"name": "DL-trigger_Failure",
				"description": "Activity to log failure of trigger file deletion",
				"type": "SqlServerStoredProcedure",
				"dependsOn": [
					{
						"activity": "Delete_After_Condition_Check",
						"dependencyConditions": [
							"Failed"
						]
					}
				],
				"policy": {
					"timeout": "7.00:00:00",
					"retry": 0,
					"retryIntervalInSeconds": 30,
					"secureOutput": false,
					"secureInput": false
				},
				"userProperties": [],
				"typeProperties": {
					"storedProcedureName": "[dbo].[generic_activity_error_audit_log]",
					"storedProcedureParameters": {
						"activity_name": {
							"value": {
								"value": "DL-Trigger",
								"type": "Expression"
							},
							"type": "String"
						},
						"activity_status": {
							"value": {
								"value": "Failed",
								"type": "Expression"
							},
							"type": "String"
						},
						"application_name": {
							"value": {
								"value": "@activity('LU-Metadata-LookUp').output.value[0].application_name",
								"type": "Expression"
							},
							"type": "String"
						},
						"dataset_name": {
							"value": {
								"value": "@activity('LU-Metadata-LookUp').output.value[0].dataset_name",
								"type": "Expression"
							},
							"type": "String"
						},
						"error_code": {
							"value": {
								"value": "NA",
								"type": "Expression"
							},
							"type": "String"
						},
						"error_detail": {
							"value": {
								"value": "NA",
								"type": "Expression"
							},
							"type": "String"
						},
						"pipeline_run_id": {
							"value": {
								"value": "@{pipeline().RunId}",
								"type": "Expression"
							},
							"type": "String"
						}
					}
				},
				"linkedServiceName": {
					"referenceName": "LS_SQL",
					"type": "LinkedServiceReference"
				}
			},
			{
				"name": "SP-PipelineStart_Snowflake",
				"description": "This Activity logs starting of pipeline in khc_audit_log table.",
				"type": "SqlServerStoredProcedure",
				"dependsOn": [],
				"policy": {
					"timeout": "7.00:00:00",
					"retry": 0,
					"retryIntervalInSeconds": 30,
					"secureOutput": false,
					"secureInput": false
				},
				"userProperties": [],
				"typeProperties": {
					"storedProcedureName": "[dbo].[generic_pipeline_audit_log]",
					"storedProcedureParameters": {
						"action_ind": {
							"value": "I",
							"type": "String"
						},
						"application_name": {
							"value": "amobee",
							"type": "String"
						},
						"dataset_name": {
							"value": {
								"value": "@pipeline().parameters.dataset_name",
								"type": "Expression"
							},
							"type": "String"
						},
						"pipeline_name": {
							"value": {
								"value": "@pipeline().Pipeline",
								"type": "Expression"
							},
							"type": "String"
						},
						"pipeline_run_id": {
							"value": {
								"value": "@pipeline().RunId",
								"type": "Expression"
							},
							"type": "String"
						},
						"pipeline_status": {
							"value": {
								"value": "Processing",
								"type": "Expression"
							},
							"type": "String"
						}
					}
				},
				"linkedServiceName": {
					"referenceName": "LS_SQL",
					"type": "LinkedServiceReference"
				}
			},
			{
				"name": "SP-PipelineSucessful_Snowflake",
				"description": "This Activity logs completion of pipeline in khc_audit_log table.",
				"type": "SqlServerStoredProcedure",
				"dependsOn": [
					{
						"activity": "EP_DBT_processing",
						"dependencyConditions": [
							"Succeeded"
						]
					}
				],
				"policy": {
					"timeout": "7.00:00:00",
					"retry": 0,
					"retryIntervalInSeconds": 30,
					"secureOutput": false,
					"secureInput": false
				},
				"userProperties": [],
				"typeProperties": {
					"storedProcedureName": "[dbo].[generic_pipeline_audit_log]",
					"storedProcedureParameters": {
						"action_ind": {
							"value": {
								"value": "U",
								"type": "Expression"
							},
							"type": "String"
						},
						"application_name": {
							"value": {
								"value": "@activity('LU-MetaData-LookUp').output.value[0].application_name",
								"type": "Expression"
							},
							"type": "String"
						},
						"dataset_name": {
							"value": {
								"value": "@activity('LU-MetaData-LookUp').output.value[0].dataset_name",
								"type": "Expression"
							},
							"type": "String"
						},
						"pipeline_name": {
							"value": {
								"value": "@pipeline().Pipeline",
								"type": "Expression"
							},
							"type": "String"
						},
						"pipeline_run_id": {
							"value": {
								"value": "@pipeline().RunId",
								"type": "Expression"
							},
							"type": "String"
						},
						"pipeline_status": {
							"value": "Successful",
							"type": "String"
						}
					}
				},
				"linkedServiceName": {
					"referenceName": "LS_SQL",
					"type": "LinkedServiceReference"
				}
			},
			{
				"name": "Delete_After_Condition_Check",
				"description": "This activity checks the defined condition and deletes the trigger file.",
				"type": "IfCondition",
				"dependsOn": [
					{
						"activity": "LU-MetaData-LookUp",
						"dependencyConditions": [
							"Succeeded"
						]
					}
				],
				"userProperties": [],
				"typeProperties": {
					"expression": {
						"value": "@and(not(equals(activity('LU-MetaData-LookUp').output.value[0].container_name,'')),not(equals(pipeline().parameters.Trigger_file_name,'')))\n",
						"type": "Expression"
					},
					"ifTrueActivities": [
						{
							"name": "DL-trigger",
							"description": "Activity to delete the trigger file in location 'marketing/amobee/triggers/'",
							"type": "Delete",
							"dependsOn": [],
							"policy": {
								"timeout": "7.00:00:00",
								"retry": 0,
								"retryIntervalInSeconds": 30,
								"secureOutput": false,
								"secureInput": false
							},
							"userProperties": [],
							"typeProperties": {
								"dataset": {
									"referenceName": "DS_KHCDE_ADLS_Blob",
									"type": "DatasetReference",
									"parameters": {
										"container": {
											"value": "@activity('LU-MetaData-LookUp').output.value[0].container_name",
											"type": "Expression"
										},
										"stage_path": {
											"value": "@concat('marketing/amobee/triggers/',pipeline().parameters.trigger_file_name)",
											"type": "Expression"
										}
									}
								},
								"enableLogging": false,
								"storeSettings": {
									"type": "AzureBlobFSReadSettings",
									"recursive": true
								}
							}
						}
					]
				}
			}
		],
		"concurrency": 1,
		"parameters": {
			"application_name": {
				"type": "string",
				"defaultValue": "amobee"
			},
			"dataset_name": {
				"type": "string",
				"defaultValue": "N.A."
			},
			"trigger_file_name": {
				"type": "string",
				"defaultValue": "N.A."
			}
		},
		"folder": {
			"name": "Marketing_Amobee"
		},
		"annotations": []
	}
}